marimo_cad/__init__.py
marimo_cad/constants.py
marimo_cad/export.py
marimo_cad/tessellate.py
marimo_cad/utils.py
marimo_cad/widget.py
marimo_cad/static/widget.css
marimo_cad/static/widget.js
marimo_cad-0.1.0.dist-info/METADATA
marimo_cad-0.1.0.dist-info/WHEEL
marimo_cad-0.1.0.dist-info/licenses/LICENSE
marimo_cad-0.1.0.dist-info/RECORD
