Metadata-Version: 2.4
Name: marimo-cad
Version: 0.1.0
Summary: Reactive Parametric CAD for marimo notebooks
Project-URL: Homepage, https://github.com/cemrehancavdar/marimo-cad
Project-URL: Repository, https://github.com/cemrehancavdar/marimo-cad
Project-URL: Issues, https://github.com/cemrehancavdar/marimo-cad/issues
Author-email: Cemrehan Cavdar <cemrehancavdar@hotmail.com>
License: MIT
License-File: LICENSE
Keywords: 3d,anywidget,build123d,cad,marimo,parametric
Classifier: Development Status :: 3 - Alpha
Classifier: Intended Audience :: Developers
Classifier: Intended Audience :: Science/Research
Classifier: License :: OSI Approved :: MIT License
Classifier: Programming Language :: Python :: 3
Classifier: Programming Language :: Python :: 3.10
Classifier: Programming Language :: Python :: 3.11
Classifier: Programming Language :: Python :: 3.12
Classifier: Programming Language :: Python :: 3.13
Classifier: Topic :: Scientific/Engineering :: Visualization
Requires-Python: >=3.10
Requires-Dist: anywidget>=0.9.0
Requires-Dist: build123d>=0.10.0
Requires-Dist: marimo>=0.9.0
Requires-Dist: ocp-tessellate>=3.0.0
Provides-Extra: dev
Requires-Dist: pytest; extra == 'dev'
Requires-Dist: ruff; extra == 'dev'
Provides-Extra: gears
Requires-Dist: bd-warehouse>=0.1.0; extra == 'gears'
